structoscope/__init__.py
structoscope/lib.py
structoscope/test.py
structoscope-0.1.0.dist-info/LICENSE
structoscope-0.1.0.dist-info/METADATA
structoscope-0.1.0.dist-info/WHEEL
structoscope-0.1.0.dist-info/top_level.txt
structoscope-0.1.0.dist-info/RECORD
