Metadata-Version: 2.1
Name: structoscope
Version: 0.1.0
Summary: A Python library for visualizing and inspecting data structures
Home-page: UNKNOWN
Author: Matteo Sandrin
Author-email: UNKNOWN
License: MIT
Platform: UNKNOWN
